datajoint/__init__.py
datajoint/admin.py
datajoint/attribute_adapter.py
datajoint/auto_tables.py
datajoint/automake.py
datajoint/autopopulate.py
datajoint/blob.py
datajoint/condition.py
datajoint/connection.py
datajoint/declare.py
datajoint/dependencies.py
datajoint/diagram.py
datajoint/errors.py
datajoint/expression.py
datajoint/external.py
datajoint/fetch.py
datajoint/hash.py
datajoint/heading.py
datajoint/jobs.py
datajoint/logging.py
datajoint/migrate.py
datajoint/part_table.py
datajoint/plugin.py
datajoint/preview.py
datajoint/s3.py
datajoint/schemas.py
datajoint/settings.py
datajoint/settings_table.py
datajoint/table.py
datajoint/user_tables.py
datajoint/utils.py
datajoint/version.py
datajoint_gucky-0.13.7.dist-info/LICENSE.txt
datajoint_gucky-0.13.7.dist-info/METADATA
datajoint_gucky-0.13.7.dist-info/WHEEL
datajoint_gucky-0.13.7.dist-info/datajoint_gucky.pub
datajoint_gucky-0.13.7.dist-info/top_level.txt
datajoint_gucky-0.13.7.dist-info/RECORD
