Metadata-Version: 2.1
Name: datajoint-gucky
Version: 0.13.7
Summary: A relational data pipeline framework.
Home-page: https://datajoint.io
Author: Matthias Christenson (forked), Dimitri Yatsenko
Author-email: gucky@gucky.eu (forked), info@datajoint.io
License: GNU LGPL
Keywords: database organization
Platform: UNKNOWN
Requires-Python: ~=3.7
License-File: LICENSE.txt
Requires-Dist: numpy
Requires-Dist: pymysql (>=0.7.2)
Requires-Dist: pyparsing
Requires-Dist: ipython
Requires-Dist: pandas
Requires-Dist: tqdm
Requires-Dist: networkx (<=2.6.3)
Requires-Dist: pydot
Requires-Dist: minio (>=7.0.0)
Requires-Dist: matplotlib
Requires-Dist: cryptography
Requires-Dist: otumat
Requires-Dist: urllib3
